all_relative/__init__.py
all_relative/__main__.py
all_relative/cli.py
all_relative/main.py
all_relative/parsers.py
all_relative-0.1.8.dist-info/entry_points.txt
all_relative-0.1.8.dist-info/WHEEL
all_relative-0.1.8.dist-info/METADATA
all_relative-0.1.8.dist-info/RECORD
